ovos_tts_plugin_piper/__init__.py
ovos_tts_plugin_piper/espeak_wrapper.py
ovos_tts_plugin_piper/piper.py
ovos_tts_plugin_piper/version.py
ovos_tts_plugin_piper/voice_models.py
ovos_tts_plugin_piper/voices.json
ovos_tts_plugin_piper-0.2.5.dist-info/licenses/LICENSE
ovos_tts_plugin_piper-0.2.5.dist-info/METADATA
ovos_tts_plugin_piper-0.2.5.dist-info/WHEEL
ovos_tts_plugin_piper-0.2.5.dist-info/entry_points.txt
ovos_tts_plugin_piper-0.2.5.dist-info/top_level.txt
ovos_tts_plugin_piper-0.2.5.dist-info/zip-safe
ovos_tts_plugin_piper-0.2.5.dist-info/RECORD
